buildbot_abstract/__init__.py
buildbot_abstract/exceptions.py
buildbot_abstract/master.py
buildbot_abstract/token.py
buildbot_abstract/utils.py
buildbot_abstract-0.3.12.dist-info/LICENSE.md
buildbot_abstract-0.3.12.dist-info/METADATA
buildbot_abstract-0.3.12.dist-info/WHEEL
buildbot_abstract-0.3.12.dist-info/top_level.txt
buildbot_abstract-0.3.12.dist-info/RECORD
